boomgame/__init__.py
boomgame/controller/__init__.py
boomgame/controller/control.py
boomgame/controller/controller.py
boomgame/data/control/player1.txt
boomgame/data/control/player2.txt
boomgame/data/font/pf_tempesta_seven.ttf
boomgame/data/font/pf_tempesta_seven_bold.ttf
boomgame/data/font/pf_tempesta_seven_condensed.ttf
boomgame/data/font/pf_tempesta_seven_condensed_bold.ttf
boomgame/data/game/boom.json
boomgame/data/game/test.json
boomgame/data/image/BOOM.png
boomgame/data/image/alien.png
boomgame/data/image/background.png
boomgame/data/image/background_menu_1.png
boomgame/data/image/background_menu_2.png
boomgame/data/image/bomb.png
boomgame/data/image/bonus_icons.png
boomgame/data/image/bonuses.png
boomgame/data/image/border.png
boomgame/data/image/breakable_wall.png
boomgame/data/image/coin.png
boomgame/data/image/extra_game.png
boomgame/data/image/extra_icons.png
boomgame/data/image/extra_letters.png
boomgame/data/image/extra_life_1.png
boomgame/data/image/extra_life_2.png
boomgame/data/image/fireball.png
boomgame/data/image/flame.png
boomgame/data/image/flash.png
boomgame/data/image/game_icon.png
boomgame/data/image/game_over.png
boomgame/data/image/ghost.png
boomgame/data/image/giggler.png
boomgame/data/image/gunner.png
boomgame/data/image/head.png
boomgame/data/image/heart.png
boomgame/data/image/hurry_up.png
boomgame/data/image/laser.png
boomgame/data/image/lightbolt.png
boomgame/data/image/lizzy.png
boomgame/data/image/loading_bomb.png
boomgame/data/image/loading_bomb_green.png
boomgame/data/image/loading_bomb_grey.png
boomgame/data/image/loading_logo.png
boomgame/data/image/loading_screen.png
boomgame/data/image/magma.png
boomgame/data/image/mgshot.png
boomgame/data/image/missile.png
boomgame/data/image/panel.png
boomgame/data/image/plasma.png
boomgame/data/image/player1.png
boomgame/data/image/player2.png
boomgame/data/image/player_head1.png
boomgame/data/image/player_head2.png
boomgame/data/image/sarge.png
boomgame/data/image/score_10.png
boomgame-0.5.3.dist-info/licenses/LICENSE
boomgame-0.5.3.dist-info/WHEEL
boomgame-0.5.3.dist-info/entry_points.txt
boomgame-0.5.3.dist-info/METADATA
boomgame-0.5.3.dist-info/RECORD
