Metadata-Version: 2.4
Name: boomgame
Version: 0.5.3
Summary: BOOM (MacOs shareware) remake with pygame
Keywords: BOOM,PyGame,Bomberman,2D Game
Author: Raphael Reme
Author-email: Raphael Reme <raphaelreme-dev@protonmail.com>
License-Expression: MIT
License-File: LICENSE
Classifier: Development Status :: 4 - Beta
Classifier: License :: OSI Approved :: MIT License
Classifier: Natural Language :: English
Classifier: Operating System :: OS Independent
Classifier: Programming Language :: Python :: 3.9
Classifier: Programming Language :: Python :: 3.10
Classifier: Programming Language :: Python :: 3.11
Classifier: Programming Language :: Python :: 3.12
Classifier: Programming Language :: Python :: 3.13
Requires-Dist: importlib-resources ; python_full_version < '3.10'
Requires-Dist: pygame-ce
Requires-Dist: typing-extensions ; python_full_version < '3.11'
Maintainer: Raphael Reme
Maintainer-email: Raphael Reme <raphaelreme-dev@protonmail.com>
Requires-Python: >=3.9
Project-URL: Documentation, https://github.com/raphaelreme/boomgame
Project-URL: Homepage, https://github.com/raphaelreme/boomgame
Project-URL: Issues, https://github.com/raphaelreme/boomgame/issues
Project-URL: Play, https://raphaelreme.github.io/boomgame
Project-URL: Repository, https://github.com/raphaelreme/boomgame
